<annotation>
	<folder>MyFaceImages</folder>
	<filename>img02859.jpg</filename>
	<path>D:\MyFaceImages\img02859.jpg</path>
	<source>
		<database>Unknown</database>
	</source>
	<size>
		<width>462</width>
		<height>280</height>
		<depth>3</depth>
	</size>
	<segmented>0</segmented>
	<object>
		<name>mask</name>
		<pose>Unspecified</pose>
		<truncated>0</truncated>
		<difficult>0</difficult>
		<bndbox>
			<xmin>332</xmin>
			<ymin>63</ymin>
			<xmax>388</xmax>
			<ymax>111</ymax>
		</bndbox>
	</object>
</annotation>
