<annotation>
	<folder>MyFaceImages</folder>
	<filename>img00168.jpg</filename>
	<path>D:\MyFaceImages\img00168.jpg</path>
	<source>
		<database>Unknown</database>
	</source>
	<size>
		<width>256</width>
		<height>256</height>
		<depth>3</depth>
	</size>
	<segmented>0</segmented>
	<object>
		<name>mask</name>
		<pose>Unspecified</pose>
		<truncated>0</truncated>
		<difficult>0</difficult>
		<bndbox>
			<xmin>51</xmin>
			<ymin>122</ymin>
			<xmax>75</xmax>
			<ymax>180</ymax>
		</bndbox>
	</object>
	<object>
		<name>mask</name>
		<pose>Unspecified</pose>
		<truncated>0</truncated>
		<difficult>0</difficult>
		<bndbox>
			<xmin>147</xmin>
			<ymin>38</ymin>
			<xmax>175</xmax>
			<ymax>87</ymax>
		</bndbox>
	</object>
	<object>
		<name>mask</name>
		<pose>Unspecified</pose>
		<truncated>0</truncated>
		<difficult>0</difficult>
		<bndbox>
			<xmin>193</xmin>
			<ymin>75</ymin>
			<xmax>221</xmax>
			<ymax>118</ymax>
		</bndbox>
	</object>
	<object>
		<name>nomask</name>
		<pose>Unspecified</pose>
		<truncated>0</truncated>
		<difficult>0</difficult>
		<bndbox>
			<xmin>2</xmin>
			<ymin>93</ymin>
			<xmax>15</xmax>
			<ymax>112</ymax>
		</bndbox>
	</object>
	<object>
		<name>nomask</name>
		<pose>Unspecified</pose>
		<truncated>0</truncated>
		<difficult>0</difficult>
		<bndbox>
			<xmin>94</xmin>
			<ymin>54</ymin>
			<xmax>110</xmax>
			<ymax>80</ymax>
		</bndbox>
	</object>
	<object>
		<name>mask</name>
		<pose>Unspecified</pose>
		<truncated>0</truncated>
		<difficult>0</difficult>
		<bndbox>
			<xmin>62</xmin>
			<ymin>82</ymin>
			<xmax>78</xmax>
			<ymax>105</ymax>
		</bndbox>
	</object>
</annotation>
