<annotation>
	<folder>MyFaceImages</folder>
	<filename>img02519.jpg</filename>
	<path>D:\MyFaceImages\img02519.jpg</path>
	<source>
		<database>Unknown</database>
	</source>
	<size>
		<width>256</width>
		<height>256</height>
		<depth>3</depth>
	</size>
	<segmented>0</segmented>
	<object>
		<name>mask</name>
		<pose>Unspecified</pose>
		<truncated>0</truncated>
		<difficult>0</difficult>
		<bndbox>
			<xmin>85</xmin>
			<ymin>59</ymin>
			<xmax>103</xmax>
			<ymax>88</ymax>
		</bndbox>
	</object>
	<object>
		<name>nomask</name>
		<pose>Unspecified</pose>
		<truncated>0</truncated>
		<difficult>0</difficult>
		<bndbox>
			<xmin>133</xmin>
			<ymin>71</ymin>
			<xmax>145</xmax>
			<ymax>104</ymax>
		</bndbox>
	</object>
</annotation>
