<annotation>
	<folder>MyImages</folder>
	<filename>img20553.jpg</filename>
	<path>D:\VOCdevkit\VOC2007\MyImages\img20553.jpg</path>
	<source>
		<database>Unknown</database>
	</source>
	<size>
		<width>1920</width>
		<height>1080</height>
		<depth>3</depth>
	</size>
	<segmented>0</segmented>
	<object>
		<name>nomask</name>
		<pose>Unspecified</pose>
		<truncated>0</truncated>
		<difficult>0</difficult>
		<bndbox>
			<xmin>1049</xmin>
			<ymin>427</ymin>
			<xmax>1064</xmax>
			<ymax>459</ymax>
		</bndbox>
	</object>
	<object>
		<name>mask</name>
		<pose>Unspecified</pose>
		<truncated>0</truncated>
		<difficult>0</difficult>
		<bndbox>
			<xmin>1623</xmin>
			<ymin>434</ymin>
			<xmax>1663</xmax>
			<ymax>475</ymax>
		</bndbox>
	</object>
	<object>
		<name>mask</name>
		<pose>Unspecified</pose>
		<truncated>0</truncated>
		<difficult>0</difficult>
		<bndbox>
			<xmin>477</xmin>
			<ymin>455</ymin>
			<xmax>502</xmax>
			<ymax>499</ymax>
		</bndbox>
	</object>
	<object>
		<name>mask</name>
		<pose>Unspecified</pose>
		<truncated>0</truncated>
		<difficult>0</difficult>
		<bndbox>
			<xmin>1314</xmin>
			<ymin>435</ymin>
			<xmax>1349</xmax>
			<ymax>470</ymax>
		</bndbox>
	</object>
</annotation>
